pylego/__init__.py
pylego/go.mod
pylego/go.sum
pylego/lego.go
pylego/lego.so
pylego/pylego.py
pylego-0.1.35.dist-info/licenses/LICENSE
pylego-0.1.35.dist-info/METADATA
pylego-0.1.35.dist-info/WHEEL
pylego-0.1.35.dist-info/top_level.txt
pylego-0.1.35.dist-info/RECORD
