Metadata-Version: 2.4
Name: pylego
Version: 0.1.35
Summary: A python wrapper package for the lego application written in Golang
Author-email: Canonical <telco-engineers@lists.canonical.com>
Project-URL: Homepage, https://github.com/canonical/pylego
Project-URL: Issues, https://github.com/canonical/pylego/issues
Classifier: Programming Language :: Python :: 3
Classifier: License :: OSI Approved :: Apache Software License
Classifier: Operating System :: OS Independent
Requires-Python: >=3.10
License-File: LICENSE
Dynamic: license-file
